starless/__init__.py
starless/__main__.py
starless/cli.py
starless/foo.py
starless/rewriter.py
starless/test_cli.py
starless/test_starless.py
starless-0.3.dist-info/METADATA
starless-0.3.dist-info/WHEEL
starless-0.3.dist-info/entry_points.txt
starless-0.3.dist-info/top_level.txt
starless-0.3.dist-info/RECORD
