Metadata-Version: 2.1
Name: starless
Version: 0.3
Summary: Star import eliminator
Home-page: http://github.com/fingon/starless
Author: Markus Stenberg
Author-email: markus.stenberg@iki.fi
License: GPLv2
Platform: UNKNOWN
Requires-Dist: redbaron
Requires-Dist: pyflakes
